llama_index/readers/psychic/__init__.py
llama_index/readers/psychic/base.py
llama_index_readers_psychic-0.4.1.dist-info/METADATA
llama_index_readers_psychic-0.4.1.dist-info/WHEEL
llama_index_readers_psychic-0.4.1.dist-info/licenses/LICENSE
llama_index_readers_psychic-0.4.1.dist-info/RECORD
