Metadata-Version: 2.4
Name: llama-index-readers-psychic
Version: 0.4.1
Summary: llama-index readers psychic integration
Author-email: Your Name <you@example.com>
License-Expression: MIT
License-File: LICENSE
Requires-Python: <4.0,>=3.9
Requires-Dist: llama-index-core<0.15,>=0.13.0
Requires-Dist: psychicapi<0.9,>=0.8.4
